arma_scipy/__init__.py
arma_scipy/fit.py
arma_scipy-1.1.dist-info/DESCRIPTION.rst
arma_scipy-1.1.dist-info/METADATA
arma_scipy-1.1.dist-info/RECORD
arma_scipy-1.1.dist-info/WHEEL
arma_scipy-1.1.dist-info/metadata.json
arma_scipy-1.1.dist-info/top_level.txt
