Metadata-Version: 2.0
Name: arma-scipy
Version: 1.1
Summary: Estimating coefficients of ARMA models with the Scipy package.
Home-page: UNKNOWN
Author: Philippe Remy
License: MIT
Platform: UNKNOWN
Requires-Dist: scipy
Requires-Dist: numpy
Requires-Dist: statsmodels
